setup.cfg
setup.py
easy_selenium/__init__.py
easy_selenium/managers.py
easy_selenium/tools.py
easy_selenium/webdriver.py
easy_selenium/webelement.py
easy_selenium/wrappers.py
easy_selenium.egg-info/PKG-INFO
easy_selenium.egg-info/SOURCES.txt
easy_selenium.egg-info/dependency_links.txt
easy_selenium.egg-info/requires.txt
easy_selenium.egg-info/top_level.txt
tests/__init__.py
tests/test_managers/__init__.py
tests/test_managers/test_context.py
tests/test_managers/test_webdriver.py
tests/test_tools/__init__.py
tests/test_tools/test_get_browser.py
tests/test_tools/test_hide_element.py
tests/test_tools/test_show_element.py
tests/test_webdriver/__init__.py
tests/test_webdriver/test_click.py
tests/test_webdriver/test_find.py
tests/test_webdriver/test_find_one.py
tests/test_webdriver/test_get_domain.py
tests/test_webdriver/test_open_popup.py
tests/test_webdriver/test_wait_for_element.py
tests/test_webdriver/test_write.py
tests/test_webelement/__init__.py
tests/test_webelement/test_element_attr.py
tests/test_webelement/test_element_find.py
tests/test_webelement/test_element_write.py
tests/test_webelement/test_popup.py