Metadata-Version: 1.1
Name: easy-selenium
Version: 0.1.1
Summary: Tool to make the use of selenium easier
Home-page: https://github.com/Tiago-Lira/easy-selenium.git
Author: Tiago Lira
Author-email: tiagoliradsantos@gmail.com
License: MIT
Download-URL: https://github.com/Tiago-Lira/easy-selenium/tarball/0.1.0
Keywords: selenium,wrapper,easy,selenium-wrapper
Platform: UNKNOWN
